blotre
