Metadata-Version: 1.0
Name: blotre
Version: 0.1.0
Summary: Thin Python Blot're client.
Home-page: https://github.com/mattbierner/blotre-py
Author: Matt Bierner
Author-email: mattbierner@users.noreply.github.com
License: MIT
Keywords: blotre,blot're,REST,oauth2
Platform: UNKNOWN
